{
  "key": "plugin_content_manager_configuration_content_types::application::result.result",
  "value": {
    "uid": "application::result.result",
    "settings": {
      "bulkable": true,
      "filterable": true,
      "searchable": true,
      "pageSize": 20,
      "mainField": "id",
      "defaultSortBy": "id",
      "defaultSortOrder": "ASC"
    },
    "metadatas": {
      "id": {
        "edit": {},
        "list": {
          "label": "Id",
          "searchable": true,
          "sortable": true
        }
      },
      "iteration": {
        "edit": {
          "label": "Iteration",
          "description": "",
          "placeholder": "",
          "visible": true,
          "editable": true
        },
        "list": {
          "label": "Iteration",
          "searchable": true,
          "sortable": true
        }
      },
      "answers": {
        "edit": {
          "label": "Answers",
          "description": "",
          "placeholder": "",
          "visible": true,
          "editable": true
        },
        "list": {
          "label": "Answers",
          "searchable": false,
          "sortable": false
        }
      },
      "user": {
        "edit": {
          "label": "User",
          "description": "",
          "placeholder": "",
          "visible": true,
          "editable": true,
          "mainField": "username"
        },
        "list": {
          "label": "User",
          "searchable": true,
          "sortable": true
        }
      },
      "survey": {
        "edit": {
          "label": "Survey",
          "description": "",
          "placeholder": "",
          "visible": true,
          "editable": true,
          "mainField": "title"
        },
        "list": {
          "label": "Survey",
          "searchable": true,
          "sortable": true
        }
      },
      "createdAt": {
        "edit": {
          "label": "CreatedAt",
          "description": "",
          "placeholder": "",
          "visible": false,
          "editable": true
        },
        "list": {
          "label": "Created At",
          "searchable": true,
          "sortable": true
        }
      },
      "updatedAt": {
        "edit": {
          "label": "UpdatedAt",
          "description": "",
          "placeholder": "",
          "visible": false,
          "editable": true
        },
        "list": {
          "label": "UpdatedAt",
          "searchable": true,
          "sortable": true
        }
      }
    },
    "layouts": {
      "edit": [
        [
          {
            "name": "iteration",
            "size": 4
          }
        ],
        [
          {
            "name": "answers",
            "size": 12
          }
        ]
      ],
      "editRelations": [
        "user",
        "survey"
      ],
      "list": [
        "id",
        "iteration",
        "user",
        "survey",
        "createdAt"
      ]
    }
  },
  "type": "object",
  "environment": "",
  "tag": ""
}